main.py
setup.py
pytorch_lighting.egg-info/PKG-INFO
pytorch_lighting.egg-info/SOURCES.txt
pytorch_lighting.egg-info/dependency_links.txt
pytorch_lighting.egg-info/requires.txt
pytorch_lighting.egg-info/top_level.txt